pulumi_pve/__init__.py
pulumi_pve/_utilities.py
pulumi_pve/provider.py
pulumi_pve/pulumi-plugin.json
pulumi_pve/py.typed
pulumi_pve/config/__init__.py
pulumi_pve/config/__init__.pyi
pulumi_pve/config/vars.py
pulumi_pve/ha/__init__.py
pulumi_pve/ha/ha.py
pulumi_pve/pool/__init__.py
pulumi_pve/pool/pool.py
pulumi_pve/storage/__init__.py
pulumi_pve/storage/_inputs.py
pulumi_pve/storage/file.py
pulumi_pve/storage/outputs.py
pulumi_pve/vm/__init__.py
pulumi_pve/vm/_inputs.py
pulumi_pve/vm/outputs.py
pulumi_pve/vm/vm.py
pulumi_pve-0.0.5.dist-info/METADATA
pulumi_pve-0.0.5.dist-info/WHEEL
pulumi_pve-0.0.5.dist-info/top_level.txt
pulumi_pve-0.0.5.dist-info/RECORD
